anywebsearch/__init__.py
anywebsearch/search.py
anywebsearch/tools.py
anywebsearch/engines/__init__.py
anywebsearch/engines/brave.py
anywebsearch/engines/duck.py
anywebsearch/engines/google.py
anywebsearch/engines/qwant.py
anywebsearch/engines/yandex.py
anywebsearch-0.1.dist-info/LICENSE
anywebsearch-0.1.dist-info/METADATA
anywebsearch-0.1.dist-info/WHEEL
anywebsearch-0.1.dist-info/top_level.txt
anywebsearch-0.1.dist-info/RECORD
