Metadata-Version: 2.1
Name: anywebsearch
Version: 0.1
Summary: Unified internet search across different search engines: Google, Bing(ddg), Brave, Qwant, Yandex
Author-email: Timur Tunkin <ch.houstone@zohomail.com>
License: Mozilla Public License Version 2.0
Project-URL: Homepage, https://github.com/tphlru/anywebsearch
Project-URL: Changelog, https://github.com/tphlru/anywebsearch/releases
Project-URL: Issues, https://github.com/tphlru/anywebsearch/issues
Project-URL: CI, https://github.com/tphlru/anywebsearch/actions
Classifier: License :: OSI Approved :: Mozilla Public License 2.0 (MPL 2.0)
Classifier: Development Status :: 4 - Beta
Classifier: Intended Audience :: Developers
Classifier: Natural Language :: English
Classifier: Programming Language :: Python :: 3.8
Classifier: Programming Language :: Python :: 3.9
Classifier: Programming Language :: Python :: 3.10
Classifier: Programming Language :: Python :: 3.11
Classifier: Programming Language :: Python :: 3.12
Classifier: Programming Language :: Python :: 3.13
Classifier: Topic :: Internet
Requires-Python: >=3.8.9
License-File: LICENSE
Requires-Dist: googlesearch-python
Requires-Dist: brave-search
Requires-Dist: duckduckgo-search >=5.0
Requires-Dist: w3lib >=2.1.2
Requires-Dist: requests >=2.31.0
Requires-Dist: xmltodict
